iqbench/base.py
iqbench/ensemble/__init__.py
iqbench/ensemble/confidence_ensemble.py
iqbench/ensemble/ensemble_base.py
iqbench/ensemble/ensemble_factory.py
iqbench/ensemble/majority_ensemble.py
iqbench/ensemble/reasoning_ensemble.py
iqbench/ensemble/reasoning_ensemble_with_image.py
iqbench/evaluation/__init__.py
iqbench/evaluation/evaluation_base.py
iqbench/evaluation/evaluation_basic.py
iqbench/evaluation/evaluation_factory.py
iqbench/evaluation/evaluation_judge.py
iqbench/models/__init__.py
iqbench/models/llm_judge.py
iqbench/models/vllm.py
iqbench/preprocessing/__init__.py
iqbench/preprocessing/base_processor.py
iqbench/preprocessing/bongard_processor.py
iqbench/preprocessing/data_module.py
iqbench/preprocessing/processor_factory.py
iqbench/preprocessing/standard_processor.py
iqbench/preprocessing/standard_sheetmaker.py
iqbench/prompts/__init__.py
iqbench/prompts/prompts_one_line.txt
iqbench/prompts/bp/problem_description_1.txt
iqbench/prompts/bp/problem_description_7.txt
iqbench/prompts/bp/sample_answer_1.txt
iqbench/prompts/bp/sample_answer_7.txt
iqbench/prompts/bp/classification/example_1.txt
iqbench/prompts/bp/classification/example_2.txt
iqbench/prompts/bp/classification/example_3.txt
iqbench/prompts/bp/classification/example_7.txt
iqbench/prompts/bp/classification/question_1.txt
iqbench/prompts/bp/classification/question_3.txt
iqbench/prompts/bp/classification/question_7.txt
iqbench/prompts/bp/contrastive/contrast_example_1.txt
iqbench/prompts/bp/contrastive/contrast_example_2.txt
iqbench/prompts/bp/contrastive/contrast_example_3.txt
iqbench/prompts/bp/contrastive/contrast_example_7.txt
iqbench/prompts/bp/contrastive/describe_1.txt
iqbench/prompts/bp/contrastive/describe_3.txt
iqbench/prompts/bp/contrastive/describe_7.txt
iqbench/prompts/bp/contrastive/example_1.txt
iqbench/prompts/bp/contrastive/example_2.txt
iqbench/prompts/bp/contrastive/example_3.txt
iqbench/prompts/bp/contrastive/example_7.txt
iqbench/prompts/bp/contrastive/question_1.txt
iqbench-0.1.2.dist-info/licenses/LICENSE
iqbench-0.1.2.dist-info/METADATA
iqbench-0.1.2.dist-info/WHEEL
iqbench-0.1.2.dist-info/top_level.txt
iqbench-0.1.2.dist-info/RECORD
