Metadata-Version: 2.4
Name: iqbench
Version: 0.1.2
Summary: A framework for comprehensive evaluation of Vision Language Models on visual analogy tasks.
Author: Karolina Dunal, Zofia Kamińska
License-Expression: Apache-2.0
Requires-Python: >=3.10
License-File: LICENSE
Requires-Dist: streamlit>=1.45.0
Requires-Dist: numpy==2.2.6
Requires-Dist: pandas==2.2.3
Requires-Dist: matplotlib==3.10.3
Requires-Dist: seaborn==0.13.2
Requires-Dist: Pillow==11.1.0
Requires-Dist: torch==2.8.0
Requires-Dist: scipy==1.15.2
Requires-Dist: vllm==0.11.0
Requires-Dist: pydantic==2.12.3
Requires-Dist: openai==2.2.0
Requires-Dist: portpicker==1.6.0
Requires-Dist: requests==2.31.0
Requires-Dist: transformers==4.55.2
Requires-Dist: python-dotenv
Requires-Dist: traitlets>=5.0.0
Dynamic: license-file
